{
  "version": 1,
  "origin": "dev.rightech.io",
  "time": "2020-11-06T13:23:42.963Z",
  "user": "5b3c895ad4100417007d22b7",
  "group": "5190951088b5078432000001",
  "store": "automatons",
  "data": {
    "_id": "5fa43cdce8fe2451f0741499",
    "name": "Аutomaton 01",
    "description": "Turn-on RGB lights depending on temperature",
    "models": [
      "5fa545db606cb61e081ded95"
    ],
    "model": "5fa545db606cb61e081ded95",
    "data": "{\"states\":{\"0\":{\"data\":{\"type\":\"init\",\"id\":\"0\",\"width\":20,\"height\":20,\"onenter\":[],\"onexit\":[]},\"position\":{\"top\":100,\"left\":80}},\"1\":{\"data\":{\"type\":\"final\",\"id\":\"1\",\"width\":20,\"height\":20,\"onenter\":[],\"onexit\":[]},\"position\":{\"top\":100,\"left\":1560}},\"2\":{\"data\":{\"type\":\"state\",\"id\":\"2\",\"name\":\"Start\",\"description\":\"Automaton start\",\"onenter\":[{\"id\":\"send-push-message\",\"name\":\"Message to operator\",\"args\":{\"importance\":{\"id\":\"importance\",\"dataType\":\"type:option, options:[information,important,critical]\"},\"message-body\":{\"id\":\"message-body\",\"dataType\":\"text\",\"value\":\"Automaton is loaded\"}}}],\"onexit\":[],\"width\":280,\"height\":180},\"position\":{\"top\":220,\"left\":400}},\"jxvlkkqu\":{\"data\":{\"type\":\"state\",\"id\":\"jxvlkkqu\",\"name\":\"Turn-off\",\"description\":\"Turn-off any lights\",\"onenter\":[{\"id\":\"led-off\",\"name\":\"Turn-off\",\"args\":{}}],\"height\":180,\"width\":280,\"onexit\":[]},\"position\":{\"top\":360,\"left\":80}},\"jxvllv18\":{\"data\":{\"type\":\"state\",\"id\":\"jxvllv18\",\"name\":\"Coldly\",\"description\":\"Temperature < 20\",\"onenter\":[{\"id\":\"led-blue\",\"name\":\"Turn-on blue\",\"args\":{}},{\"id\":\"send-push-message\",\"name\":\"Message to operator\",\"args\":{\"importance\":{\"id\":\"importance\",\"dataType\":\"type:option, options:[information,important,critical]\"},\"message-body\":{\"id\":\"message-body\",\"dataType\":\"text\",\"value\":\"Coldly\"}}}],\"height\":180,\"width\":280,\"onexit\":[]},\"position\":{\"top\":680,\"left\":100}},\"jxvllvj9\":{\"data\":{\"type\":\"state\",\"id\":\"jxvllvj9\",\"name\":\"Fine\",\"description\":\"Temperature 20..30\",\"onenter\":[{\"id\":\"led-green\",\"name\":\"Turn-on green\",\"args\":{}},{\"id\":\"send-push-message\",\"name\":\"Message to operator\",\"args\":{\"importance\":{\"id\":\"importance\",\"dataType\":\"type:option, options:[information,important,critical]\"},\"message-body\":{\"id\":\"message-body\",\"dataType\":\"text\",\"value\":\"Fine\"}}}],\"height\":180,\"width\":280,\"onexit\":[]},\"position\":{\"top\":580,\"left\":600}},\"jxvllvxp\":{\"data\":{\"type\":\"state\",\"id\":\"jxvllvxp\",\"name\":\"Hot\",\"description\":\"Temperature > 30\",\"onenter\":[{\"id\":\"led-red\",\"name\":\"Turn-on red\",\"args\":{}},{\"id\":\"send-push-message\",\"name\":\"Message to operator\",\"args\":{\"importance\":{\"id\":\"importance\",\"dataType\":\"type:option, options:[information,important,critical]\"},\"message-body\":{\"id\":\"message-body\",\"dataType\":\"text\",\"value\":\"Hot\"}}}],\"height\":180,\"width\":280,\"onexit\":[]},\"position\":{\"top\":400,\"left\":1000}}},\"transitions\":{\"0\":{\"drawMode\":\"rou\",\"points\":[{\"x\":100,\"y\":100},{\"x\":160,\"y\":100},{\"x\":160,\"y\":100},{\"x\":200,\"y\":100},{\"x\":200,\"y\":160},{\"x\":420,\"y\":160},{\"x\":420,\"y\":200}],\"data\":{\"id\":\"0\",\"name\":\"Инициализация логики\",\"description\":\"Событие, возникающее при запуске интерпретации модели логики\",\"event\":\"init\",\"owner\":{\"id\":\"0\",\"point\":{\"location\":\"right\",\"id\":0}},\"target\":{\"id\":\"2\",\"point\":{\"location\":\"top\",\"id\":1}},\"autoDescription\":false,\"eventParameters\":{},\"blockKey\":\"cb-0\",\"targetIndex\":-1},\"version\":3,\"block\":{\"data\":{\"type\":\"connectionBlock\",\"connectionKey\":\"0\"},\"layout\":{\"minHeight\":2,\"minWidth\":6,\"movable\":true,\"resizable\":true,\"margin\":1,\"updateConnections\":[\"0\"],\"canOverlap\":true,\"pfInvisible\":true,\"height\":6,\"width\":11,\"position\":{\"x\":5,\"y\":2}},\"key\":\"cb-0\"}},\"jxvll0o6\":{\"drawMode\":\"rou\",\"points\":[{\"x\":380,\"y\":260},{\"x\":300,\"y\":260},{\"x\":300,\"y\":260},{\"x\":200,\"y\":260},{\"x\":120,\"y\":260},{\"x\":120,\"y\":340}],\"data\":{\"owner\":{\"id\":\"2\",\"point\":{\"id\":2,\"location\":\"left\"}},\"target\":{\"id\":\"jxvlkkqu\",\"point\":{\"id\":2,\"location\":\"top\"}},\"id\":\"jxvll0o6\",\"event\":\"immediate-transition\",\"name\":\"Immediate transition\",\"eventParameters\":{},\"autoDescription\":true,\"blockKey\":\"cb-jxvll0o6\",\"targetIndex\":-1},\"version\":3,\"block\":{\"data\":{\"type\":\"connectionBlock\",\"connectionKey\":\"jxvll0o6\"},\"layout\":{\"minHeight\":2,\"minWidth\":6,\"movable\":true,\"resizable\":true,\"margin\":1,\"updateConnections\":[\"jxvll0o6\"],\"canOverlap\":true,\"pfInvisible\":true,\"width\":8,\"height\":3,\"position\":{\"x\":6,\"y\":12}},\"key\":\"cb-jxvll0o6\"}},\"jxvlodmb\":{\"drawMode\":\"rou\",\"points\":[{\"x\":160,\"y\":540},{\"x\":160,\"y\":580},{\"x\":160,\"y\":580},{\"x\":160,\"y\":600},{\"x\":120,\"y\":600},{\"x\":80,\"y\":600},{\"x\":80,\"y\":640},{\"x\":100,\"y\":640},{\"x\":100,\"y\":660}],\"data\":{\"owner\":{\"id\":\"jxvlkkqu\",\"point\":{\"id\":4,\"location\":\"bottom\"}},\"target\":{\"id\":\"jxvllv18\",\"point\":{\"id\":0,\"location\":\"top\"}},\"id\":\"jxvlodmb\",\"event\":\"es-recive-device-data\",\"name\":\"Data received\",\"eventParameters\":{},\"condition\":\"{\\\"0\\\":{\\\"0\\\":{\\\"data\\\":{\\\"type\\\":\\\"parametr\\\",\\\"arg\\\":\\\"eff_temp\\\",\\\"source\\\":\\\"state\\\",\\\"identifier\\\":\\\"object\\\"},\\\"type\\\":\\\"parametr\\\"},\\\"1\\\":{\\\"data\\\":{\\\"arg\\\":\\\"20\\\",\\\"type\\\":\\\"value\\\"},\\\"type\\\":\\\"parametr\\\"},\\\"data\\\":{\\\"type\\\":\\\"less\\\"},\\\"type\\\":\\\"condition\\\"}}\",\"userCode\":\"object[\\\"state\\\"][\\\"eff_temp\\\"] < 20\",\"autoDescription\":true,\"description\":\"Выполнить переход если: Параметр \\\"Effective temperature\\\" < 20\",\"blockKey\":\"cb-jxvlodmb\",\"targetIndex\":-1},\"version\":3,\"block\":{\"data\":{\"type\":\"connectionBlock\",\"connectionKey\":\"jxvlodmb\"},\"layout\":{\"minHeight\":2,\"minWidth\":6,\"movable\":true,\"resizable\":true,\"margin\":1,\"updateConnections\":[\"jxvlodmb\"],\"canOverlap\":true,\"pfInvisible\":true,\"width\":8,\"height\":3,\"position\":{\"x\":2,\"y\":29}},\"key\":\"cb-jxvlodmb\"}},\"jxvloxs2\":{\"drawMode\":\"rou\",\"points\":[{\"x\":360,\"y\":460},{\"x\":460,\"y\":460},{\"x\":460,\"y\":460},{\"x\":560,\"y\":460},{\"x\":560,\"y\":520},{\"x\":620,\"y\":520},{\"x\":620,\"y\":560}],\"data\":{\"owner\":{\"id\":\"jxvlkkqu\",\"point\":{\"id\":5,\"location\":\"right\"}},\"target\":{\"id\":\"jxvllvj9\",\"point\":{\"id\":1,\"location\":\"top\"}},\"id\":\"jxvloxs2\",\"event\":\"es-recive-device-data\",\"name\":\"Data received\",\"eventParameters\":{},\"condition\":\"{\\\"0\\\":{\\\"0\\\":{\\\"0\\\":{\\\"data\\\":{\\\"type\\\":\\\"parametr\\\",\\\"arg\\\":\\\"eff_temp\\\",\\\"source\\\":\\\"state\\\",\\\"identifier\\\":\\\"object\\\"},\\\"type\\\":\\\"parametr\\\"},\\\"1\\\":{\\\"data\\\":{\\\"arg\\\":\\\"20\\\",\\\"type\\\":\\\"value\\\"},\\\"type\\\":\\\"parametr\\\"},\\\"data\\\":{\\\"type\\\":\\\"more-equal\\\"},\\\"type\\\":\\\"condition\\\"},\\\"1\\\":{\\\"0\\\":{\\\"data\\\":{\\\"type\\\":\\\"parametr\\\",\\\"arg\\\":\\\"eff_temp\\\",\\\"source\\\":\\\"state\\\",\\\"identifier\\\":\\\"object\\\"},\\\"type\\\":\\\"parametr\\\"},\\\"1\\\":{\\\"data\\\":{\\\"arg\\\":\\\"30\\\",\\\"type\\\":\\\"value\\\"},\\\"type\\\":\\\"parametr\\\"},\\\"data\\\":{\\\"type\\\":\\\"less-equal\\\"},\\\"type\\\":\\\"condition\\\"},\\\"data\\\":{\\\"type\\\":\\\"and\\\"},\\\"type\\\":\\\"condition\\\"}}\",\"userCode\":\"object[\\\"state\\\"][\\\"eff_temp\\\"] >= 20\\n && object[\\\"state\\\"][\\\"eff_temp\\\"] <= 30\",\"autoDescription\":true,\"description\":\"Выполнить переход если: Параметр \\\"Effective temperature\\\" >= 20 И Параметр \\\"Effective temperature\\\" <= 30\",\"blockKey\":\"cb-jxvloxs2\",\"targetIndex\":-1},\"version\":3,\"block\":{\"data\":{\"type\":\"connectionBlock\",\"connectionKey\":\"jxvloxs2\"},\"layout\":{\"minHeight\":2,\"minWidth\":6,\"movable\":true,\"resizable\":true,\"margin\":1,\"updateConnections\":[\"jxvloxs2\"],\"canOverlap\":true,\"pfInvisible\":true,\"width\":8,\"height\":3,\"position\":{\"x\":24,\"y\":22}},\"key\":\"cb-jxvloxs2\"}},\"jxvlppuq\":{\"drawMode\":\"rou\",\"points\":[{\"x\":360,\"y\":400},{\"x\":520,\"y\":400},{\"x\":520,\"y\":420},{\"x\":680,\"y\":420},{\"x\":840,\"y\":420},{\"x\":840,\"y\":420},{\"x\":980,\"y\":420}],\"data\":{\"owner\":{\"id\":\"jxvlkkqu\",\"point\":{\"id\":2,\"location\":\"right\"}},\"target\":{\"id\":\"jxvllvxp\",\"point\":{\"id\":1,\"location\":\"left\"}},\"id\":\"jxvlppuq\",\"event\":\"es-recive-device-data\",\"name\":\"Получены данные\",\"eventParameters\":{},\"condition\":\"{\\\"0\\\":{\\\"0\\\":{\\\"data\\\":{\\\"type\\\":\\\"parametr\\\",\\\"arg\\\":\\\"eff_temp\\\",\\\"source\\\":\\\"state\\\",\\\"identifier\\\":\\\"object\\\"},\\\"type\\\":\\\"parametr\\\"},\\\"1\\\":{\\\"data\\\":{\\\"arg\\\":\\\"30\\\",\\\"type\\\":\\\"value\\\"},\\\"type\\\":\\\"parametr\\\"},\\\"data\\\":{\\\"type\\\":\\\"more\\\"},\\\"type\\\":\\\"condition\\\"}}\",\"userCode\":\"object[\\\"state\\\"][\\\"eff_temp\\\"] > 30\",\"autoDescription\":false,\"description\":\"Transit if: object[\\\"state\\\"][\\\"eff_temp\\\"] > 30\",\"blockKey\":\"cb-jxvlppuq\",\"targetIndex\":-1},\"version\":3,\"block\":{\"data\":{\"type\":\"connectionBlock\",\"connectionKey\":\"jxvlppuq\"},\"layout\":{\"minHeight\":2,\"minWidth\":6,\"movable\":true,\"resizable\":true,\"margin\":1,\"updateConnections\":[\"jxvlppuq\"],\"canOverlap\":true,\"pfInvisible\":true,\"width\":8,\"height\":3,\"position\":{\"x\":30,\"y\":20}},\"key\":\"cb-jxvlppuq\"}},\"jxvlq4l7\":{\"drawMode\":\"rou\",\"points\":[{\"x\":380,\"y\":720},{\"x\":440,\"y\":720},{\"x\":440,\"y\":680},{\"x\":480,\"y\":680},{\"x\":540,\"y\":680},{\"x\":540,\"y\":680},{\"x\":580,\"y\":680}],\"data\":{\"owner\":{\"id\":\"jxvllv18\",\"point\":{\"id\":2,\"location\":\"right\"}},\"target\":{\"id\":\"jxvllvj9\",\"point\":{\"id\":5,\"location\":\"left\"}},\"id\":\"jxvlq4l7\",\"event\":\"es-recive-device-data\",\"name\":\"Data received\",\"eventParameters\":{},\"condition\":\"{\\\"0\\\":{\\\"0\\\":{\\\"0\\\":{\\\"data\\\":{\\\"type\\\":\\\"parametr\\\",\\\"arg\\\":\\\"eff_temp\\\",\\\"source\\\":\\\"state\\\",\\\"identifier\\\":\\\"object\\\"},\\\"type\\\":\\\"parametr\\\"},\\\"1\\\":{\\\"data\\\":{\\\"arg\\\":\\\"20\\\",\\\"type\\\":\\\"value\\\"},\\\"type\\\":\\\"parametr\\\"},\\\"data\\\":{\\\"type\\\":\\\"more-equal\\\"},\\\"type\\\":\\\"condition\\\"},\\\"1\\\":{\\\"0\\\":{\\\"data\\\":{\\\"type\\\":\\\"parametr\\\",\\\"arg\\\":\\\"eff_temp\\\",\\\"source\\\":\\\"state\\\",\\\"identifier\\\":\\\"object\\\"},\\\"type\\\":\\\"parametr\\\"},\\\"1\\\":{\\\"data\\\":{\\\"arg\\\":\\\"30\\\",\\\"type\\\":\\\"value\\\"},\\\"type\\\":\\\"parametr\\\"},\\\"data\\\":{\\\"type\\\":\\\"less-equal\\\"},\\\"type\\\":\\\"condition\\\"},\\\"data\\\":{\\\"type\\\":\\\"and\\\"},\\\"type\\\":\\\"condition\\\"}}\",\"userCode\":\"object[\\\"state\\\"][\\\"eff_temp\\\"] >= 20\\n && object[\\\"state\\\"][\\\"eff_temp\\\"] <= 30\",\"autoDescription\":true,\"description\":\"Выполнить переход если: Параметр \\\"Effective temperature\\\" >= 20 И Параметр \\\"Effective temperature\\\" <= 30\",\"blockKey\":\"cb-jxvlq4l7\",\"targetIndex\":-1},\"version\":3,\"block\":{\"data\":{\"type\":\"connectionBlock\",\"connectionKey\":\"jxvlq4l7\"},\"layout\":{\"minHeight\":2,\"minWidth\":6,\"movable\":true,\"resizable\":true,\"margin\":1,\"updateConnections\":[\"jxvlq4l7\"],\"canOverlap\":true,\"pfInvisible\":true,\"width\":7,\"height\":3,\"position\":{\"x\":21,\"y\":33}},\"key\":\"cb-jxvlq4l7\"}},\"jxvlr1dm\":{\"drawMode\":\"rou\",\"points\":[{\"x\":380,\"y\":780},{\"x\":620,\"y\":780},{\"x\":620,\"y\":780},{\"x\":840,\"y\":780},{\"x\":840,\"y\":680},{\"x\":1060,\"y\":680},{\"x\":1060,\"y\":580}],\"data\":{\"owner\":{\"id\":\"jxvllv18\",\"point\":{\"id\":5,\"location\":\"right\"}},\"target\":{\"id\":\"jxvllvxp\",\"point\":{\"id\":3,\"location\":\"bottom\"}},\"id\":\"jxvlr1dm\",\"event\":\"es-recive-device-data\",\"name\":\"Data received\",\"eventParameters\":{},\"condition\":\"{\\\"0\\\":{\\\"0\\\":{\\\"data\\\":{\\\"type\\\":\\\"parametr\\\",\\\"arg\\\":\\\"eff_temp\\\",\\\"source\\\":\\\"state\\\",\\\"identifier\\\":\\\"object\\\"},\\\"type\\\":\\\"parametr\\\"},\\\"1\\\":{\\\"data\\\":{\\\"arg\\\":\\\"30\\\",\\\"type\\\":\\\"value\\\"},\\\"type\\\":\\\"parametr\\\"},\\\"data\\\":{\\\"type\\\":\\\"more\\\"},\\\"type\\\":\\\"condition\\\"}}\",\"userCode\":\"object[\\\"state\\\"][\\\"eff_temp\\\"] > 30\",\"autoDescription\":true,\"description\":\"Выполнить переход если: Параметр \\\"Effective temperature\\\" > 30\",\"blockKey\":\"cb-jxvlr1dm\",\"targetIndex\":-1},\"version\":3,\"block\":{\"data\":{\"type\":\"connectionBlock\",\"connectionKey\":\"jxvlr1dm\"},\"layout\":{\"minHeight\":2,\"minWidth\":6,\"movable\":true,\"resizable\":true,\"margin\":1,\"updateConnections\":[\"jxvlr1dm\"],\"canOverlap\":true,\"pfInvisible\":true,\"width\":8,\"height\":3,\"position\":{\"x\":38,\"y\":38}},\"key\":\"cb-jxvlr1dm\"}},\"jxvlritt\":{\"drawMode\":\"rou\",\"points\":[{\"x\":740,\"y\":760},{\"x\":740,\"y\":840},{\"x\":520,\"y\":840},{\"x\":520,\"y\":900},{\"x\":380,\"y\":900},{\"x\":380,\"y\":900},{\"x\":240,\"y\":900},{\"x\":240,\"y\":860}],\"data\":{\"owner\":{\"id\":\"jxvllvj9\",\"point\":{\"id\":7,\"location\":\"bottom\"}},\"target\":{\"id\":\"jxvllv18\",\"point\":{\"id\":7,\"location\":\"bottom\"}},\"id\":\"jxvlritt\",\"event\":\"es-recive-device-data\",\"name\":\"Data received\",\"eventParameters\":{},\"condition\":\"{\\\"0\\\":{\\\"0\\\":{\\\"data\\\":{\\\"type\\\":\\\"parametr\\\",\\\"arg\\\":\\\"eff_temp\\\",\\\"source\\\":\\\"state\\\",\\\"identifier\\\":\\\"object\\\"},\\\"type\\\":\\\"parametr\\\"},\\\"1\\\":{\\\"data\\\":{\\\"arg\\\":\\\"20\\\",\\\"type\\\":\\\"value\\\"},\\\"type\\\":\\\"parametr\\\"},\\\"data\\\":{\\\"type\\\":\\\"less\\\"},\\\"type\\\":\\\"condition\\\"}}\",\"userCode\":\"object[\\\"state\\\"][\\\"eff_temp\\\"] < 20\",\"autoDescription\":true,\"description\":\"Выполнить переход если: Параметр \\\"Effective temperature\\\" < 20\",\"blockKey\":\"cb-jxvlritt\",\"targetIndex\":-1},\"version\":3,\"block\":{\"data\":{\"type\":\"connectionBlock\",\"connectionKey\":\"jxvlritt\"},\"layout\":{\"minHeight\":2,\"minWidth\":6,\"movable\":true,\"resizable\":true,\"margin\":1,\"updateConnections\":[\"jxvlritt\"],\"canOverlap\":true,\"pfInvisible\":true,\"width\":8,\"height\":3,\"position\":{\"x\":22,\"y\":44}},\"key\":\"cb-jxvlritt\"}},\"jxvlrwo9\":{\"drawMode\":\"rou\",\"points\":[{\"x\":880,\"y\":580},{\"x\":920,\"y\":580},{\"x\":920,\"y\":580},{\"x\":940,\"y\":580},{\"x\":940,\"y\":540},{\"x\":940,\"y\":500},{\"x\":960,\"y\":500},{\"x\":960,\"y\":500},{\"x\":980,\"y\":500}],\"data\":{\"owner\":{\"id\":\"jxvllvj9\",\"point\":{\"id\":0,\"location\":\"right\"}},\"target\":{\"id\":\"jxvllvxp\",\"point\":{\"id\":5,\"location\":\"left\"}},\"id\":\"jxvlrwo9\",\"event\":\"es-recive-device-data\",\"name\":\"Data received\",\"eventParameters\":{},\"condition\":\"{\\\"0\\\":{\\\"0\\\":{\\\"data\\\":{\\\"type\\\":\\\"parametr\\\",\\\"arg\\\":\\\"eff_temp\\\",\\\"source\\\":\\\"state\\\",\\\"identifier\\\":\\\"object\\\"},\\\"type\\\":\\\"parametr\\\"},\\\"1\\\":{\\\"data\\\":{\\\"arg\\\":\\\"30\\\",\\\"type\\\":\\\"value\\\"},\\\"type\\\":\\\"parametr\\\"},\\\"data\\\":{\\\"type\\\":\\\"more\\\"},\\\"type\\\":\\\"condition\\\"}}\",\"userCode\":\"object[\\\"state\\\"][\\\"eff_temp\\\"] > 30\",\"autoDescription\":true,\"description\":\"Выполнить переход если: Параметр \\\"Effective temperature\\\" > 30\",\"blockKey\":\"cb-jxvlrwo9\",\"targetIndex\":-1},\"version\":3,\"block\":{\"data\":{\"type\":\"connectionBlock\",\"connectionKey\":\"jxvlrwo9\"},\"layout\":{\"minHeight\":2,\"minWidth\":6,\"movable\":true,\"resizable\":true,\"margin\":1,\"updateConnections\":[\"jxvlrwo9\"],\"canOverlap\":true,\"pfInvisible\":true,\"width\":8,\"height\":3,\"position\":{\"x\":43,\"y\":26}},\"key\":\"cb-jxvlrwo9\"}},\"jxvls8xl\":{\"drawMode\":\"rou\",\"points\":[{\"x\":1100,\"y\":580},{\"x\":1100,\"y\":640},{\"x\":1000,\"y\":640},{\"x\":940,\"y\":640},{\"x\":940,\"y\":640},{\"x\":880,\"y\":640}],\"data\":{\"owner\":{\"id\":\"jxvllvxp\",\"point\":{\"id\":5,\"location\":\"bottom\"}},\"target\":{\"id\":\"jxvllvj9\",\"point\":{\"id\":3,\"location\":\"right\"}},\"id\":\"jxvls8xl\",\"event\":\"es-recive-device-data\",\"name\":\"Data received\",\"eventParameters\":{},\"condition\":\"{\\\"0\\\":{\\\"0\\\":{\\\"0\\\":{\\\"data\\\":{\\\"type\\\":\\\"parametr\\\",\\\"arg\\\":\\\"eff_temp\\\",\\\"source\\\":\\\"state\\\",\\\"identifier\\\":\\\"object\\\"},\\\"type\\\":\\\"parametr\\\"},\\\"1\\\":{\\\"data\\\":{\\\"arg\\\":\\\"20\\\",\\\"type\\\":\\\"value\\\"},\\\"type\\\":\\\"parametr\\\"},\\\"data\\\":{\\\"type\\\":\\\"more-equal\\\"},\\\"type\\\":\\\"condition\\\"},\\\"1\\\":{\\\"0\\\":{\\\"data\\\":{\\\"type\\\":\\\"parametr\\\",\\\"arg\\\":\\\"eff_temp\\\",\\\"source\\\":\\\"state\\\",\\\"identifier\\\":\\\"object\\\"},\\\"type\\\":\\\"parametr\\\"},\\\"1\\\":{\\\"data\\\":{\\\"arg\\\":\\\"30\\\",\\\"type\\\":\\\"value\\\"},\\\"type\\\":\\\"parametr\\\"},\\\"data\\\":{\\\"type\\\":\\\"less-equal\\\"},\\\"type\\\":\\\"condition\\\"},\\\"data\\\":{\\\"type\\\":\\\"and\\\"},\\\"type\\\":\\\"condition\\\"}}\",\"userCode\":\"object[\\\"state\\\"][\\\"eff_temp\\\"] >= 20\\n && object[\\\"state\\\"][\\\"eff_temp\\\"] <= 30\",\"autoDescription\":true,\"description\":\"Выполнить переход если: Параметр \\\"Effective temperature\\\" >= 20 И Параметр \\\"Effective temperature\\\" <= 30\",\"blockKey\":\"cb-jxvls8xl\",\"targetIndex\":-1},\"version\":3,\"block\":{\"data\":{\"type\":\"connectionBlock\",\"connectionKey\":\"jxvls8xl\"},\"layout\":{\"minHeight\":2,\"minWidth\":6,\"movable\":true,\"resizable\":true,\"margin\":1,\"updateConnections\":[\"jxvls8xl\"],\"canOverlap\":true,\"pfInvisible\":true,\"width\":8,\"height\":3,\"position\":{\"x\":46,\"y\":31}},\"key\":\"cb-jxvls8xl\"}},\"jxvlsszt\":{\"drawMode\":\"rou\",\"points\":[{\"x\":1160,\"y\":580},{\"x\":1160,\"y\":740},{\"x\":800,\"y\":740},{\"x\":800,\"y\":900},{\"x\":500,\"y\":900},{\"x\":500,\"y\":900},{\"x\":200,\"y\":900},{\"x\":200,\"y\":860}],\"data\":{\"owner\":{\"id\":\"jxvllvxp\",\"point\":{\"id\":8,\"location\":\"bottom\"}},\"target\":{\"id\":\"jxvllv18\",\"point\":{\"id\":5,\"location\":\"bottom\"}},\"id\":\"jxvlsszt\",\"event\":\"es-recive-device-data\",\"name\":\"Data received\",\"eventParameters\":{},\"condition\":\"{\\\"0\\\":{\\\"0\\\":{\\\"data\\\":{\\\"type\\\":\\\"parametr\\\",\\\"arg\\\":\\\"eff_temp\\\",\\\"source\\\":\\\"state\\\",\\\"identifier\\\":\\\"object\\\"},\\\"type\\\":\\\"parametr\\\"},\\\"1\\\":{\\\"data\\\":{\\\"arg\\\":\\\"20\\\",\\\"type\\\":\\\"value\\\"},\\\"type\\\":\\\"parametr\\\"},\\\"data\\\":{\\\"type\\\":\\\"less\\\"},\\\"type\\\":\\\"condition\\\"}}\",\"userCode\":\"object[\\\"state\\\"][\\\"eff_temp\\\"] < 20\",\"autoDescription\":true,\"description\":\"Выполнить переход если: Параметр \\\"Effective temperature\\\" < 20\",\"blockKey\":\"cb-jxvlsszt\",\"targetIndex\":-1},\"version\":3,\"block\":{\"data\":{\"type\":\"connectionBlock\",\"connectionKey\":\"jxvlsszt\"},\"layout\":{\"minHeight\":2,\"minWidth\":6,\"movable\":true,\"resizable\":true,\"margin\":1,\"updateConnections\":[\"jxvlsszt\"],\"canOverlap\":true,\"pfInvisible\":true,\"width\":8,\"height\":3,\"position\":{\"x\":36,\"y\":44}},\"key\":\"cb-jxvlsszt\"}}}}",
    "objects": [
      "5d8209b7a860f700110c7a0d"
    ]
  }
}